{
    "imprimatur": null,
    "corrector": false,
    "entête": {
        "form": "prose",
        "genre": "non renseigné",
        "subgenre": [
            null,
            null
        ],
        "subject": null,
        "handwritten_note": false,
        "table_of_content": false,
        "illustration": false,
        "change": {
            "@status": "not_corrected"
        },
        "titre": "Nouveaux (les) jeux du piquet de la Cour.",
        "dates": {
            "@type": "file_creation",
            "@when": "2021-11-02",
            "#text": "2 novembre 2021"
        },
        "author": {
            "persName": {
                "forename": null,
                "surname": null
            }
        },
        "pubDate": {
            "@source": "Moreau",
            "@when": "Sans Date",
            "#text": "Sans Date"
        },
        "pubPlace": {
            "@ref": "geonames:0000000",
            "@source": "Moreau",
            "#text": "Sans Lieu"
        },
        "publisher": {
            "@ref": "isni:0000000",
            "persName": {
                "forename": null,
                "surname": null
            }
        },
        "nbPages": "4"
    },
    "texte": [
        [
            "71",
            "Seesoe",
            "e",
            "l",
            "l aaA¬",
            "l m",
            "vs",
            "6",
            "¬",
            "e¬",
            "T",
            "e!",
            "al",
            "ſ4",
            "1",
            "lVJea!",
            "ua",
            "A",
            "L aa",
            "Re",
            "2",
            "d ¬",
            "la ,",
            "E!",
            "E",
            "aay8",
            "ee",
            "S",
            "’Ee",
            "a lrla"
        ],
        [
            ".¬",
            "1",
            "e.",
            "et",
            ".",
            "2y",
            "2.",
            "-",
            "3",
            ".",
            "7",
            ".3",
            "1",
            "s &amp;",
            "e",
            "?",
            "¬",
            "¬",
            "¬",
            "é",
            ",",
            "y",
            "2",
            "¬",
            "’",
            "V",
            "3",
            "ur",
            "L",
            "S",
            "&amp;",
            "e",
            "¬",
            "3",
            "11",
            "T",
            "4",
            "2",
            "gy",
            "S",
            "¬¬",
            "2",
            ":",
            "!",
            "S’8",
            "Qe¬",
            ".",
            "A",
            "s",
            "1",
            "rg",
            "?",
            "A",
            "Sa,",
            "N",
            "’e",
            ";",
            "S1",
            "aaé",
            "¬",
            "e",
            "a",
            "s",
            "e",
            "e",
            "N",
            "a",
            "?",
            "8",
            "1",
            "5¬",
            "re",
            "al e",
            "2¬",
            "s",
            ":",
            "E",
            ".",
            "6",
            "s",
            "¬",
            "E",
            "-",
            "n",
            "2",
            "&amp;",
            "lP2",
            "?",
            "2",
            "!",
            "23",
            "r",
            "t",
            "e 6",
            "r",
            ":",
            "a",
            "L",
            "7.",
            "l.",
            "e",
            "e",
            "a¬",
            "2",
            "g",
            "’e¬",
            "SN",
            "¬",
            "yS",
            "Pa",
            "S",
            "a",
            "A",
            "¬",
            "a2",
            ".",
            "as",
            "T",
            "¬",
            "r",
            "’e.",
            "’",
            "¬.",
            "E",
            "a",
            "â.",
            "ae",
            "i",
            ".",
            "E",
            "2",
            "l e i",
            "as",
            "-E",
            "2",
            "¬¬",
            ".",
            "¬",
            "¬",
            "2",
            ",,",
            "a",
            "¬",
            "e",
            "e",
            "-",
            "S",
            "i?",
            "¬",
            "¬",
            "9",
            "3",
            "2!",
            "1",
            "3 E",
            "4",
            "i¬",
            "le",
            "Z",
            "u?",
            "I",
            "P",
            ".",
            "Sade",
            "3¬",
            "a",
            "9",
            "A",
            "8",
            ";",
            "¬",
            "lr",
            "J",
            "l!",
            "a",
            "lleas",
            "lds",
            "E",
            "ee?",
            "l¬",
            "l",
            "¬",
            "e",
            "u",
            "6",
            "!",
            "ae",
            "r",
            "E",
            "ré ;",
            "8",
            "l",
            "s",
            "3",
            "3",
            "-",
            ".",
            "r 1",
            "ees",
            "1",
            "e",
            "¬",
            "ts",
            "i",
            "¬",
            "2",
            "es",
            "5",
            "E",
            "e S",
            "e d",
            "n",
            "p;¬",
            "i",
            "-",
            "¬",
            "e"
        ],
        [
            "ee",
            "2",
            "le e1s",
            "3",
            "¬",
            "l",
            "il ̃",
            "¬¬",
            "-a",
            "S",
            "-a",
            "a",
            "A",
            "S",
            "1-",
            "a",
            "e3",
            "3",
            "Vl ¬",
            "e3",
            "-l",
            "la",
            "2",
            "l",
            "s",
            "1",
            "9",
            "371",
            ".",
            "1:.",
            "2",
            "l",
            "!",
            "e",
            "5",
            "ẽ",
            "3",
            "’-",
            "N",
            "¬",
            "2",
            "s",
            "s",
            "I6",
            "a",
            "P",
            "-.¬",
            "¬",
            "e",
            "a",
            "z",
            "V.",
            "E",
            "¬",
            "t",
            "A",
            "4",
            "e¬",
            "Ee",
            "a",
            "L",
            "6",
            "a8",
            "¬",
            "e",
            "e¬",
            "¬,",
            "?",
            "a",
            ",",
            "a",
            "s",
            "’",
            "S",
            "M",
            "E",
            "li",
            "s",
            "S",
            "¬",
            "-",
            "e.",
            ".",
            "11",
            "2",
            "-ee",
            "¬",
            "g",
            "t eg",
            "r",
            "e",
            ".",
            "E",
            "e",
            "a",
            "e",
            "S",
            "e;",
            "P",
            "Ee",
            "¬",
            "e",
            "3",
            "27",
            "e",
            "¬",
            "!",
            "8",
            "Ei",
            "E",
            "i",
            "¬",
            "e",
            "E",
            "¬",
            "e",
            "e",
            "¬",
            "¬",
            "ee",
            "ee¬",
            "r2",
            "Hs",
            "?",
            "8",
            "AE",
            "e",
            "a",
            "e",
            "aa",
            "I",
            "a",
            "ES",
            "S",
            "a2",
            "a",
            "s",
            "3",
            "s,",
            "?",
            "E",
            "!",
            "c",
            "e",
            "-",
            "ai",
            "2",
            "a",
            "i",
            "l¬",
            "Ae",
            "re",
            "¬",
            "e",
            "e",
            "¬¬",
            "edee",
            "s",
            "a",
            "et2",
            "E",
            "-’",
            "¬",
            "3",
            "A",
            "aẽ",
            "-",
            "3",
            "a",
            "3",
            "u¬",
            "ae8",
            "-E",
            "ã",
            "¬",
            "d e¬",
            "?",
            "ld",
            "z",
            "1",
            "4g",
            "e¬",
            "AS!",
            "S",
            "¬",
            "’",
            "e",
            "S",
            "¬",
            "4",
            "2",
            "E",
            "r",
            "¬",
            "¬",
            "a",
            "¬",
            "E",
            "l-a",
            "l",
            "N",
            "¬",
            "rà",
            "¬",
            "l¬",
            "¬¬",
            "¬¬",
            "ss",
            "!",
            "-2",
            ".",
            "3¬",
            "1",
            "Q",
            "E",
            "’1",
            "z",
            "S",
            "-e",
            "ee",
            "e;",
            "¬",
            "E",
            "ege"
        ],
        [
            "1",
            "1",
            "l",
            "l",
            "liſMtlſil",
            "e",
            "?",
            "1",
            "9",
            "T",
            "1!",
            "ſllſeſl",
            "eit",
            "ellſopl",
            "r",
            "del",
            "1",
            "ele",
            "d8",
            "s",
            "lſali",
            "d",
            "ts",
            "E",
            "Id",
            "2p",
            "rE",
            "l",
            "lſ",
            "ps",
            ",",
            "Sel",
            "q",
            "E",
            "Vi",
            "¬",
            "115",
            "ldt",
            "e",
            "ldi",
            "é",
            "3",
            "!",
            "¬",
            "t?",
            "ei",
            "ui14",
            "n",
            "u",
            "deſe",
            "ſ",
            "e",
            "’l epldelelddeearedoé",
            "l",
            "eeeiladſeli",
            "t",
            "laajas;",
            "esdt",
            "é",
            "i",
            "llel",
            "eet",
            "S;",
            "e",
            "i",
            ",",
            "i",
            "e",
            "ti",
            "egr",
            "3",
            "ii",
            "Sedſipliieſo",
            "El",
            "lt",
            "iiſtſea",
            "1?",
            "i!",
            "p!",
            "tii!",
            "leilddln",
            "Iſllſiui",
            "Jé",
            "i",
            "3",
            "1",
            "eu",
            "74",
            "lleern",
            "25",
            "1!",
            "e",
            "liaiu",
            "1u",
            "s",
            "êi",
            "ll",
            "rn",
            "t",
            "?",
            "ili8",
            "isſ",
            "lſdl",
            "e1s",
            "ſie1",
            "t",
            "e",
            "11",
            "l",
            "11",
            "es",
            "a",
            "ii",
            "23",
            "e",
            "r3",
            "r",
            "é",
            "1",
            "p51",
            "llu",
            "l",
            "dlur",
            "leſllſlſ",
            "a",
            "tt",
            "3",
            "I",
            "3p25",
            "e",
            "l2!",
            "ed",
            "1",
            "lilieieeſfeen",
            "Pe",
            "e",
            "2",
            "d",
            "lnn",
            "34!",
            "3",
            "lſn",
            "54",
            "uſ",
            "3i1",
            "l",
            "lſll",
            "Spyj",
            "llll",
            "l",
            "i",
            "1",
            "1!",
            "E",
            "i",
            "lil",
            "ſliſll",
            "AII",
            "II",
            "l",
            "Il",
            "ſli",
            "ll",
            "eltillll?",
            "iſſſdlll",
            "llils",
            "31",
            "S",
            "l",
            "lil",
            "1",
            "nt",
            "leu",
            "lpiei",
            "HHe1",
            "leeeie dlden",
            ";",
            "lle",
            "r",
            "rp",
            "a",
            "i",
            "e8¬",
            "eiſ",
            "i?",
            "te1",
            "ts",
            "tt",
            "ldil",
            "1s",
            "s",
            "Le",
            "lh",
            "ld",
            "i",
            "p",
            "lteſ",
            "ii",
            "lldnun",
            "i",
            "lr",
            "nei",
            "lIuſdee",
            "ſ lſesfien",
            "s",
            "llP rrſ alſelll",
            "i",
            ",",
            "1",
            "i",
            "lalll",
            ";",
            "12",
            "3",
            "1",
            "e",
            "8",
            "4",
            "14",
            "ſ",
            "ee eſiedli",
            "1E",
            "s",
            "all?",
            "e",
            "13",
            "l",
            "l elee",
            "e",
            "Re",
            "ltſ",
            "8",
            "rmre e",
            "ſedl",
            "t!",
            "e",
            "llliſirlen",
            "lſtl",
            "leeeſdas",
            "ei ſiſ",
            "ss",
            "lt",
            "ldſ",
            "E",
            "l!",
            "a",
            "ir",
            "eſelſas",
            "dll1",
            "lrr",
            "ldlll",
            "i",
            "lli",
            "lii4",
            "ls",
            "llle",
            "i",
            "Irl",
            "ia",
            "le",
            "it",
            "dllll",
            "lel",
            "1",
            "lſiei",
            "ldereſlii",
            "l",
            "1it",
            "ſu?",
            "lſi",
            "lF",
            "l",
            "dſeſn",
            "le",
            "¬",
            "ulnelul",
            "n",
            "!",
            "olie",
            "lll",
            "t¬",
            "Ie",
            "r",
            "111s",
            "il",
            "rrnl",
            "llſlſldl",
            "1",
            "II",
            "i",
            "ſi",
            "lllii",
            "lll",
            "1",
            "lſ",
            "e",
            "u;",
            "1",
            "lllela",
            "il",
            "il",
            "16",
            "ſſlſi",
            "llll!",
            "ai",
            "l",
            "Mll1",
            "l",
            "le dldldſſ",
            "ril",
            "i",
            "q",
            "alis",
            "hlſ",
            "Iiſdl",
            "1",
            "ti",
            "5tp3",
            "trill",
            "rie",
            "ſ6",
            "E",
            "sſ",
            "lput",
            "ll",
            "eſierl",
            "i",
            "e ldd",
            "trgedſelir",
            "g4",
            "lſu",
            "lli",
            "ali",
            "1",
            "reſn",
            "s",
            "ſll",
            "il",
            "eE",
            "?",
            "1",
            "n!",
            "de?",
            "lrt",
            "l dſdreidlleſlll",
            "ldeſrſneln",
            "llſlii",
            "IPlie",
            "er",
            "lſ lpee",
            "l",
            "P",
            "lldſllſlnai",
            "e",
            "e",
            "Palſdeſſeeſtlſlaſlſd",
            "n",
            "n",
            "llu",
            "edlilellt",
            "I",
            "erlſſlſ",
            "jn",
            "ddede ereiea",
            "i4",
            "e",
            "5e",
            "2¬",
            "lel",
            "eed",
            "pre erp etrt e ieſ treilleeir",
            "11",
            "ſle",
            "n",
            "Js",
            "3",
            "S",
            "eſe",
            "iſde",
            "p",
            "lige",
            "sſl",
            "lſ8",
            "rt",
            "lnldlri",
            "ee",
            "i",
            "e",
            "lti?",
            "ltn",
            "tHi",
            "eg",
            "ee",
            "ll",
            "er",
            "Ps",
            "ie",
            "lſlié",
            "e",
            "i1",
            "’in",
            "u",
            "’",
            "ll",
            "eas",
            "rt",
            "t",
            "1sl",
            "Is",
            "lſliſ1",
            "llei etſeiui",
            "1p1",
            "li",
            "e lldrſl",
            "li",
            "ll",
            "ilili!",
            "2",
            "1",
            "1",
            "3",
            "1",
            "1",
            "3",
            "8",
            "p"
        ],
        [
            "S371",
            "L ,",
            "2S420."
        ],
        [
            "¬",
            "Pi1",
            "11",
            "e",
            "11i",
            "ledlil",
            "lſle",
            "5p",
            "nnl",
            "An",
            "ſs",
            "8",
            "lll e i",
            "llin",
            "l",
            "lſſas",
            "ll",
            "eſſ",
            "T",
            "ſlſ",
            "1",
            "3ſie!",
            "ll",
            "lt u",
            "1",
            "Se i",
            "rdel!",
            "1e",
            "lſilelisſs dlel",
            "dlſlls",
            "liſdl",
            "l",
            "ll1",
            "11i!",
            "e",
            "!",
            "Iiiſil",
            "1ill",
            "ln",
            "u",
            "r!",
            "S",
            "lMtr",
            "llu",
            "133",
            ",",
            "rſſd1",
            "n",
            "7",
            "l",
            "lu",
            "lilll",
            "15",
            "ſl",
            "4A;i",
            "pAs",
            "j",
            "ei",
            "ips",
            "Ire",
            "1tr",
            "ieile",
            "i",
            "l",
            "riies",
            "ii",
            ";",
            "lſadſſnſ",
            "1t",
            "s",
            "rpiltſd",
            "1",
            "19",
            "!",
            "t",
            "l",
            "?1?",
            "lſli",
            ",",
            "2",
            "11",
            "lE1!",
            "1",
            "i",
            "1",
            "li!",
            "ſe",
            "rt",
            "t",
            "l",
            "l",
            "11",
            "i¬",
            "êis!",
            "e",
            "e",
            "ſi",
            "S8",
            "e",
            "gſſelli",
            "et",
            "Ve",
            "ql",
            "u",
            "i3tes",
            "i",
            "11",
            "3",
            "1",
            "1t",
            "le",
            "l",
            "ilſi",
            "lei",
            "Eſi",
            "l",
            "l3",
            "du",
            "a",
            "135",
            "s",
            "L",
            "lis",
            "l",
            "4",
            "3",
            "lleſſi",
            "gs",
            "Jiſr",
            "’i ſlu",
            "dſ",
            "lliit",
            "piu",
            "Hi",
            "3",
            "llſ",
            "tiql",
            "1",
            "1",
            "p",
            "etes",
            "e",
            "tetlt rrlſſſs!eeſr!",
            "l",
            "11",
            "es",
            "er1",
            "t¬",
            "à",
            "3!",
            "liſi",
            "Aéii",
            "ſe",
            "iti",
            "lln",
            "t",
            "Iſ",
            "dl1i",
            "1",
            "3",
            "la",
            "loieue",
            "Jts",
            "f!",
            "3",
            "i8",
            "le",
            "p",
            "ti",
            "uj",
            "ileterr",
            "1!",
            "p",
            "ſii",
            "1",
            "r",
            "ss",
            "l",
            "1!ei",
            "6",
            "J",
            "dire",
            "lſti1",
            "let",
            "leiſfe",
            "lii",
            "ſepelarlll",
            "l",
            "1",
            "eoeiſii",
            "Peddlie",
            "s",
            "a",
            "ie",
            "ldel",
            "11",
            "ll",
            "4",
            "m",
            "Pl",
            "3",
            "ſa",
            "3t",
            "l in",
            "5",
            "1",
            "!",
            "Ierelſltſrſfnlſlſlaſeſeeil",
            "tte!",
            "reiſſlild",
            "ldſil",
            "Edla",
            "p",
            "leidtddſe?",
            "Ifſd",
            "ue",
            "ledelieſldulias",
            "4ſr¬",
            "uu",
            "5",
            "Ellſd",
            "lhlſe ederſin",
            "irl",
            "Eedſſt",
            "24i",
            "rr?",
            "I4!",
            "!i",
            "1",
            "1",
            "Plle",
            "lio",
            "llſi",
            "Eſſi",
            "lldſll",
            "eeſlſed",
            "4",
            "laei",
            "llll lllſdl",
            "ddie",
            "l",
            "’iſltrlle",
            "lrdldſal",
            "u",
            "¬",
            "lnrs1",
            "ſſi",
            "1",
            "lldelellſitlſiln!",
            "I",
            "t",
            "llſi ſlil",
            "lllillliſ",
            "l",
            "Et",
            "S!",
            "ll lerle",
            "ldsrei",
            "eilde",
            "lelſeel e",
            "tr8",
            ":",
            "lſlt",
            "’¬",
            "ini",
            "tpii",
            "ſſſit",
            "lſ",
            "eoder alei ſflieell",
            "lie",
            "t1",
            "etlltnl",
            "u",
            "SlAi",
            "8",
            "l’",
            "tſl",
            "e",
            "i",
            "l ſepe ldl",
            "I eli",
            "pſeiet",
            "lit",
            "ledldllſeil",
            "ter;s",
            "eu",
            "IIſſſii",
            "leſſlilſiſelſi",
            "lln ſilſl",
            "renſdſſlei",
            "lire",
            "ddet",
            "t",
            "llil",
            "ſ",
            "ldſlieſſſiill",
            "Eſiſiſſilei",
            ";5",
            "l&amp;lilleiſ",
            "llll",
            "ir",
            "lli",
            "r",
            "llſ",
            "ltis",
            "eee1",
            "tl1",
            "lſieſ llil",
            "1",
            "l",
            "die lſliſſiſn",
            "t",
            "e",
            "lſ",
            "4",
            "E2",
            "elipti",
            "ftlſ erneolleelſtdſuſe",
            "leele",
            "t",
            "ſlprſlrelil",
            "lje",
            "llll",
            "t",
            "sr",
            "1",
            "op",
            "1!",
            "llil edli",
            "ll",
            "oelſellii",
            "3",
            "Eit",
            "I1",
            "lareeen",
            "peill e ſutrl ldi",
            "fees",
            "lld",
            "s!",
            "ldeſile",
            "is",
            "1sé",
            "t",
            "lt",
            "ſs",
            "He",
            "lertee",
            "rits",
            "E",
            "lſſili",
            "lie",
            "lie",
            "1",
            "lliu",
            "llti",
            "or",
            "llli",
            "t iſlf",
            "ltſ¬",
            "reſtſpi",
            "e41",
            "Sedeſſlſl",
            "llileſe",
            "illdſl",
            "1",
            "33",
            "J1i",
            "llelde lll",
            "s",
            "3Iitl",
            "e",
            "leldſlſleeerilſi",
            "llll dl",
            "1",
            "ſſen",
            "Eie",
            "5i?;?",
            "llllllli",
            "it",
            "lelel",
            "lllrlſllſ",
            "ſllin",
            "e el4si",
            "re",
            "1",
            "eiſ",
            "ldlldl",
            "Fllrſil",
            "llledll",
            "Iſ",
            "Ie?",
            "ld",
            "etilt1",
            "i",
            "et¬",
            "1",
            "lls",
            "t1",
            "ee llſſe",
            "lllitet",
            "33EE",
            "s5?",
            "lſſſ",
            "i",
            "1",
            "l",
            "d ſdſiſdſieaius",
            "1i",
            "llidr",
            "IIi",
            "n",
            "le leſilul",
            "tieier",
            "l",
            "s",
            "3",
            "ies",
            "5",
            "1",
            "lrll",
            "lllnll",
            "lldils",
            "Elâià",
            "tin",
            "iejrj",
            "lli",
            "pill",
            "4",
            "dolſb liei?",
            "litſſi",
            "I",
            "lſilſe",
            "iſt",
            "llllſi",
            "lſoleeireoqe ſil",
            "tl",
            "2",
            "lſſilſl1",
            "Il",
            "t",
            "leeli",
            "?",
            "1",
            "ll",
            "j7",
            "Eicii",
            "ldlllelenſl",
            "1é1",
            "2",
            "eſilſilll",
            "Vlitdſſpdt",
            "la",
            "tſl",
            "eee",
            "edli",
            "¬",
            "24",
            "121",
            "l1",
            "lts",
            "Irlelli",
            "!",
            "8",
            "!",
            "!",
            "4",
            "11",
            "1",
            "!"
        ],
        [
            "4S5",
            "m&amp;ueeA",
            "LES",
            "T",
            "T",
            "NOVVEAVIEV",
            "1 !",
            "du Piequet de la Cour.",
            "-et de la",
            "LE ROY.",
            "JE panie, ue ſoa an pe ſle",
            "Mon leu eſt bien broüillé, pour n’auoir Cd’vne",
            "couleur Rouge.",
            "Mazarin.",
            "L’on ne ioüe en France comme en ltalie, l’on me",
            "veut forcer d’écarter, Ce n’eſt pas mon leu.",
            "Les Nieces de Mazarin.",
            "2",
            "Noſtre leu nous paroiſſoit beau au commencement,",
            "mais la chance a tourné qui nousarenuoyé bien loing.",
            "Les Filles de la Reyne.",
            "Nous regardons pour apprendre le leu.",
            "Monſieur le Duc d’Orleans.",
            "’l’auois beau &amp; ie cours riſque de perdre la partie, pour",
            "auoir ereu mauuais conſeil, &amp; ſi cela arriue ie jetteray le",
            "ieu dans la Riuiere, &amp; apres i’écarteray à propos.",
            "Monſieur le Prince.",
            "Il faut bien ballancer, i’ay du cœur &amp; du pique, ie ne",
            "ſçay de quel coſtéie dois tomber, il faut voir le leu des",
            "vns &amp; des autres, &amp; ne faire voir le mien que le dernier.",
            "Monſiear de Longueuille.",
            "I’ay peine à comprendre tout cecy, quand les cartes",
            "ſont bien brouillées l’on m’appelle au Ieu, ceux qui ont",
            "tofité, les doiuent desbouiller, oubien reſtituer."
        ],
        [
            "1",
            "44",
            "¬¬",
            "Monſieur le Prinoe de Conmty.¬",
            "Ie commence aà connoiſtre le Ieu des vns &amp; desautres,.",
            "i’en feray mon profiten temps &amp; ſieu.",
            "adamoi ſelle.",
            "Que i’aurois beau ieu s’il me venoit vn Roy.",
            "Monſieur de la Meilleraye.",
            "Le carreau ne m’accomode point, il me pourroit cau¬",
            "ſer dommage. Monſieur le Chancellier.",
            "La picque ma déja penſé faire perdre, s’il continuë̈",
            "me venir,ie ietteray le Ieu dans la bouë, bien que i’y aye",
            "treuué mon compte. Monſfieur Tubeuf.",
            "Tout le ieu m’empeſche d’auoit le mot pour rire com¬",
            "me de couſtume n’y, pouuant treuuer mon compre à̀",
            "moins de faire capot.",
            "Monſieur de Sennererre.",
            "le parie ma perte s’il ne me vient vn repie.",
            "Monſieur le Cheualier du Iars.",
            "le crains l’eſeart de coulleur rouge.",
            "Les Partiſans.",
            "L’on a veu noſtre ieu, &amp; par noſtre tromperie nous",
            "perdrons la partie.",
            "Meſſieurs du Parlement.",
            "A la fin l’on connoiſt que noſtre Ieu n’eſtoit que fide¬",
            "lite, &amp; noſtce intereſt eſt à l’vn des principaux Ioueurs.",
            "L’Archiduc Leopold.:",
            "Ie penſois gaigner quelque choſe à ce leu, mais ie cõ¬",
            "hois a preſent que ie n’y gaigneray rien",
            "Autre Ieu du Picquet de la Cour.",
            "LaReyne.",
            "JE porte vn As qui me fait bien,",
            "l’ay fort beau leu, mais ſans eſcart.",
            "lL"
        ],
        [
            "s5",
            "491",
            "Le Roy.",
            "Ie ne ſç̧aypas encore le leu, mais ie l’apprendray.",
            "Monſieur le Dac d’Anion.",
            "Ien’y connois rien, mais i’y ioü̈eray quelque iour.",
            "Le Candinal.",
            "Au hazard’ie prens tout,",
            "Et iovoglio pigliar la robba di la Francia.",
            "Monſieur le Ducd’Orleans.",
            "I’ay beau Ieu, mais le cœur me manque¬",
            "Monſieur le Prince de Conde.",
            "I’ay bien du cœur, mais ie ne ſçay que porter, car i’ap¬",
            "pehende le carreau.",
            "Monſieur le Priuce de Conty.",
            "Pour garder mon eœur, faut eſcarter ceét Az.",
            "Momfieur le Due de Longueuille.",
            "le ne puis gaigner, car l’on m’a triché.",
            "Le Roy.",
            "A force de perdre, i’apprendray le Ieu.",
            "I. Reyo¬",
            "Ile ne ſongeois pas qu’il faut eſcarter.",
            "Le Cardinal.¬",
            "Ioſono beneimpedito &amp; crede che utto e perditt0",
            "per che il mioiuocque ecatiuo.",
            "Madamoiſelle de Beauuais à Phbilandre.",
            "Nous ne ſcauons plus que ioüer.",
            "Les ’Filles de la Reyne.",
            "Nous apprendrons en voyant le ieu.",
            "La Reyne d’Angleterre.",
            "Ie vois bien que tout eſt perdu, car ie connois les ieux.",
            "Madamiſelle.",
            "Si i’auois vnRoy, ie ſçaurois bien que faire."
        ],
        [
            ". 3",
            "¬¬",
            "Meſſieurs du Parlement.",
            "Pour nous ſauuer du cappot faut écarter cétAz.",
            "Monſieur de Beaufort.",
            "Vne Dame &amp;vn Az me faiſoient cappot, c’eſtoitpar",
            "tricherie, ie l’ay deſcouuert.",
            "Monſieur le Chanmcellier.",
            "Mon Ieu ne vaut rien, &amp; peu en a ſalu que ie n’aye",
            "tout perdu. Monſfieur le Surintendaent.",
            "Ie me ſuis perdu moy meſme par trop battre.",
            "Monſieur de Chaſteau- neuf",
            "Ie m’en vais touſiours dutout.",
            "Monſieur de Chauigny &amp; ſa Femme.",
            "Par vn malheureux eſcart nous ſommes cappor.",
            "Monſieur d’Auaux.",
            "Ile ne gaigne rienau leu, car ie veux demeſler.",
            "Monſeur Seruien.",
            "Pour gaigner ie meſle touſiours.",
            "Madame de Combalee.",
            "Ie ne fais plus rlen, re veux plus ioier.",
            "Les Nieces du Cardinmal.",
            "Es biſogne che noi andauiſſimo, dautto per che noſſe",
            "Iuocque non val niente.,",
            "Monſieur Baurru, Nogent &amp; Senneterre.",
            "Noſtre Ieu eſt retourne.",
            "Meſſieurs les Secretaires d’Eſtat &amp; Iatendans.",
            "Nous ne ſeruons plus qu’aà marquer le ieu.",
            "Monſieur d’Emery.",
            "Ie ſuis bien pris, ie n’ay plus beau ieu.",
            "Meſſieurs les Courtizans.",
            "Noſtre ieu nous reſſemble.",
            "’F.",
            "mma¬"
        ],
        [
            "L",
            "lll",
            "1!",
            "t",
            "à",
            "s",
            "e",
            "!",
            "llls",
            "i1",
            "ſriſ",
            "i!",
            "E",
            "15e",
            "e",
            "lllis",
            "lſfe",
            "as",
            "t",
            "5,",
            "1E",
            "ei",
            "t",
            "1s",
            "eet",
            "s",
            "lla",
            "sſe",
            "é",
            "E!",
            "e",
            "l",
            "4",
            "eslele",
            "7",
            "1!",
            "1",
            "1",
            "bi",
            "t",
            "lt",
            "5",
            "!",
            "1a",
            "lill",
            "l",
            "eiſſil",
            "llilſi",
            "a",
            "sl!",
            "3",
            ",Jr",
            "3",
            "dlii",
            "8",
            "g.",
            "l",
            "l",
            "1",
            "1",
            "lt",
            "1",
            "l",
            "lſd",
            "t",
            "l",
            "l1",
            "s8",
            "a",
            "i",
            "p?",
            "l",
            "8",
            "n",
            "i8",
            "ltſtt",
            "2",
            "d?",
            "leerlll",
            "13",
            "3s",
            "33û",
            "ſ",
            "ie",
            "ilitii",
            "3a",
            "1",
            "te",
            "le",
            "Pſel lele",
            "Lut",
            "1i",
            "ei",
            "t",
            "1",
            "4",
            "¬",
            "t",
            "n",
            "E",
            "4",
            "F5",
            "l",
            "letl",
            "e",
            "lte",
            "i",
            "pe",
            "ſ",
            "de¬",
            "p",
            "pl",
            "a",
            "’lisi",
            "1",
            "t",
            "ll",
            "i",
            "1e1",
            "det",
            "lſeilſu",
            "3",
            "ſ",
            "1",
            "p",
            "1i",
            "nrit",
            "Pitl",
            "t",
            "ldet",
            "3s",
            "lre",
            "e",
            "i",
            "f",
            "1",
            "ſſ",
            "l",
            "iſptdi",
            "le",
            "pn",
            "n",
            "ss",
            "Cilſ",
            "llſii",
            "l ill",
            "I1",
            "1",
            "i",
            "ſ",
            "ilell",
            "é",
            "s",
            "lſllſl",
            "ijâ,",
            "lui",
            "t",
            "liſ!",
            "a",
            "l",
            "re",
            "llſi",
            "ſt",
            "p",
            "i",
            "i",
            "Hl",
            "u!",
            "ps",
            "l",
            "e51",
            "J",
            "ſ¬",
            "lu",
            "lu",
            "3?4",
            "1",
            "Eiedeu",
            "ſſdi",
            "He1?",
            "d",
            "4",
            "e ll",
            "ei",
            "é",
            "plſdt",
            "lt",
            "4",
            "d",
            "33",
            "1",
            "llſfſit",
            "i",
            "Iſtl",
            "E",
            "ſeldleſtqierſdſſq",
            "lldl",
            "25",
            "llil",
            "leſſld",
            "ſilleldeſa",
            "l1",
            "i",
            "g",
            "lſr",
            "1",
            "as",
            "alir",
            "Prou",
            "lldeiſiſlel",
            "1",
            "r1",
            "llu",
            "Elde",
            "elti43",
            "ſlſſis",
            "l",
            "lſſlideiedu",
            "eſedl",
            "le¬",
            "lſili",
            "e",
            "i",
            "e",
            "5",
            "llſ",
            "l",
            "s",
            "ledt",
            "e",
            "lleſdeſdſ",
            "1lis",
            "Plſis",
            "l",
            "rl",
            "peeoa",
            "4",
            "e",
            "te",
            "s",
            "?",
            "Ve",
            "ed",
            "t;",
            "la",
            ".",
            "ne ellei llls",
            "dſli",
            "t",
            "de",
            "l",
            "taat",
            "lert",
            "la",
            "ieldiſldl1",
            "1",
            "Ht",
            "rlr",
            "lea",
            "ua",
            "rr",
            "1r",
            "a",
            "ll",
            "t1",
            "1",
            "ed",
            "s",
            "tililili",
            "n",
            "E1",
            "1rlli",
            "leſien",
            "e",
            "’ſſliev",
            "ete",
            "In1",
            "q",
            "per",
            "1s",
            "2",
            "ldn",
            "lplilldlſlſili",
            "41",
            "A",
            "dedide deeſ",
            "le",
            "i",
            "llelrn",
            "tSeeſdſes",
            "i1",
            "t",
            "n",
            "ldi",
            "lEli",
            "t!",
            "rae",
            "li",
            "llis",
            "lſlle",
            "s",
            "e",
            "le",
            "3",
            "ldlſieieoee elei",
            "lil dldlſlſeſ",
            "iuu4",
            "ieſi",
            "lll",
            "pstisgss",
            "1",
            "5",
            "ſte",
            "43",
            "J",
            "piu",
            "1i",
            "ds",
            "lſllfillil",
            "e",
            "lls",
            "p",
            "!",
            "le",
            "reſſd",
            "s1",
            "lllilitſi",
            "lnlſ1",
            "l",
            "lpisi",
            "le",
            "ll",
            "i",
            "s",
            "l",
            "l",
            "l",
            "lr",
            "Ildl",
            "i!",
            "et",
            "133",
            "2",
            "ilieriel",
            "tl",
            "Ee?",
            "ellrii",
            "iſlden",
            "il!",
            "aa",
            "u",
            "’dilni",
            "lſ",
            "l",
            "li",
            "itil",
            "lu¬",
            "luſdilnnas",
            "ls",
            "l",
            "eli",
            "t",
            "t",
            "llillſld",
            "ll1",
            "l",
            "1",
            "s",
            "’il",
            "1",
            "ti1",
            "li",
            "ai",
            "eellln",
            "Ept1",
            "ldſiſi",
            "2s",
            "i¬",
            "r",
            "ſſlfpſfſs",
            "lllu",
            "l",
            "ſſ",
            "efriſſllll",
            "3",
            "ealſtſii",
            "l!",
            "1",
            "4e",
            "1t6",
            "ſsſll",
            "tt",
            "uij8",
            "liids",
            "llſlt",
            "dlis",
            "ſtdſdldldl",
            "lſelſ!",
            "r",
            "ãl",
            "leſſit",
            "yj",
            "3",
            "dllilſ",
            "edlſ eilſlſn",
            "tſelodle e rlilſi",
            "T",
            "i",
            "idt",
            "elſE",
            "1ſſſ",
            "d",
            ".",
            "n",
            "u",
            "leſie eifieltllil",
            "llere",
            "5",
            "eld",
            "ld",
            "liſuli",
            "leddſiſlte",
            "4",
            "s",
            "tſ",
            "!",
            "95",
            "i",
            "li",
            "lpir",
            "44",
            "ldaildleleiſedſole ſ eliſeieo ſioei",
            "1?",
            "It",
            ",",
            "1"
        ],
        [
            "a¬",
            "e",
            "a",
            "e",
            "SS",
            "¬",
            "s",
            "¬",
            "aa",
            "IEe",
            "e",
            "¬",
            "3 ¬",
            "e",
            "a",
            "eras 1",
            "e",
            "E",
            "E¬",
            "2 S",
            ".",
            "a",
            "ià",
            "a2",
            "d",
            "p",
            "¬",
            "S",
            "AS",
            "g",
            "a",
            "r",
            "A",
            "E",
            "Jl",
            "iu",
            "2",
            "? -2",
            "¬¬",
            "e",
            ".",
            "-ces,¬",
            "¬",
            "E",
            "E",
            "E",
            "S",
            "9",
            "A6;",
            "S",
            "-",
            ".",
            "A",
            "y",
            "E",
            ".",
            ".",
            "-",
            "7",
            "e¬",
            "a",
            "E",
            "s",
            "A",
            "z",
            "e",
            "u",
            "i",
            "1",
            "¬",
            "e",
            "?",
            "-",
            "a",
            "ii",
            "le",
            "i",
            "5",
            "?",
            "¬",
            "¬",
            "¬",
            "sa",
            ",",
            "’",
            ".",
            "1",
            "¬",
            "z",
            "e",
            ",",
            "8!",
            "-",
            "a",
            "¬",
            "s s g",
            "2",
            "?",
            "2",
            "¬",
            "i",
            "2",
            "e",
            "¬",
            ";",
            "n",
            "¬",
            "I.",
            "¬",
            "l",
            "e",
            "’re",
            "e",
            "E",
            "r",
            "s",
            "r",
            "¬",
            "c.¬",
            "C",
            "Eer",
            "r",
            "22",
            "ee",
            "¬",
            "E.",
            "A¬",
            "e",
            "S",
            "8",
            "52",
            "2 li",
            "5",
            "e",
            "¬",
            "vé",
            ".",
            "eis",
            "22",
            "23",
            "2",
            "s",
            "¬",
            "l",
            ". &amp;,",
            "Aae",
            "ee",
            "l",
            "e¬",
            "ſs",
            "¬",
            "ee",
            "¬",
            "Su",
            "8",
            "¬",
            "AaE",
            "n",
            "5",
            "E",
            "2",
            "eea",
            "js",
            "ee",
            "¬",
            "és",
            "Ili?",
            "E",
            "i",
            "1e",
            "A",
            "Hu",
            "72",
            "l",
            "&amp;e.e",
            "1",
            "ee",
            "àSs2",
            "2",
            "ie",
            "RE",
            "a,",
            "S",
            "LLe",
            "Hs",
            "A 5",
            "aaas",
            "¬",
            "’",
            "aa¬",
            "N",
            "As",
            "ees",
            "e",
            "e",
            "eia",
            "V1",
            "&amp;",
            "?",
            "2",
            "l",
            "A",
            "Ee.",
            "E",
            "eaa e",
            "3",
            "a",
            "y?",
            "j",
            "-e.",
            "e",
            "a",
            "-",
            "ea",
            "¬",
            "8",
            "Gdul",
            "ã",
            "vi",
            "&amp;6",
            "y",
            "e",
            "1",
            "2",
            ".",
            "Ae",
            "¬"
        ],
        [
            "1",
            "Als",
            "¬",
            "¬",
            "E",
            "-",
            "J",
            "3 S 6",
            "i",
            "1 2",
            "t",
            "Ht",
            "l",
            "l li",
            "8",
            "s",
            "Jes",
            "lt 52",
            "E s",
            "¬!",
            ".",
            "e",
            "ps",
            "l 2",
            "15",
            "E",
            "2",
            "1",
            "e4i",
            ".",
            "l",
            "E¬",
            "!",
            "2li",
            ".",
            "1",
            "31",
            "ſ1",
            "1",
            "3",
            "le",
            "22",
            "E",
            ".",
            "¬",
            "a",
            "4",
            "sE",
            "¬",
            "g",
            "e",
            "-ee,",
            "2",
            ".",
            "a",
            "8",
            "2",
            "A",
            "Aa¬",
            "2 2",
            "2",
            "1",
            "r",
            "-",
            ".",
            "lur",
            "74",
            "a.",
            "r",
            ".",
            "¬",
            "5¬",
            "eſddi",
            "s",
            ",",
            "¬",
            "é",
            "g",
            "e",
            "re!",
            "E",
            "171",
            "l48",
            "¬",
            "AF",
            "S",
            "e ene",
            "a",
            "Jſſs",
            "l",
            "e¬",
            ".¬",
            "L",
            "R",
            "¬",
            ",",
            "S",
            "5¬",
            "E",
            "à?",
            "2",
            "e",
            "é",
            "o",
            "D",
            "S",
            "5",
            "É",
            "3",
            "le",
            "2",
            "1",
            "1",
            "2",
            "E",
            "¬",
            "E",
            "Ee",
            "T",
            "1",
            "i",
            "E",
            "E.",
            "3",
            "i",
            "i",
            "asi",
            "!",
            "¬",
            "S",
            "?",
            "Ee",
            "22",
            "aS.",
            "e-",
            "5 5",
            "en¬",
            "Psr",
            "Sa",
            "5",
            "6",
            "ens",
            "s",
            ";",
            "e",
            "E",
            "aee",
            "1",
            "Iſt",
            "3",
            "SS",
            "-",
            "a",
            "A",
            ".",
            "¬",
            ",",
            "a",
            "eS¬",
            "ee",
            "e",
            "aa",
            "2",
            "Epz",
            "-",
            "rg",
            "¬",
            ".",
            "D",
            "e",
            "2",
            "2",
            "1",
            "a",
            "¬",
            "Q",
            "a1",
            "e",
            "s2!",
            "4",
            "eS",
            "e",
            "e¬",
            "?",
            "IE3",
            "2E",
            "1",
            "ree",
            "e",
            "e",
            "5",
            "p",
            "ie¬",
            "o",
            "1",
            "9",
            "5",
            "pe",
            "4’J",
            "ese",
            "l",
            "12",
            "i",
            "r",
            "-",
            "E",
            "¬",
            "i",
            "t2",
            "s",
            "ai",
            "A",
            "a",
            "̂",
            "1 ¬",
            "5",
            "e",
            "e?",
            "3",
            "e",
            "e",
            "9",
            "e",
            "i¬",
            "ag",
            "-",
            "a¬",
            "A",
            "eae",
            "¬¬",
            "i",
            "r",
            "1",
            "A¬",
            "ie",
            "!",
            "?",
            "It",
            ".",
            "e ;",
            "’",
            "¬",
            "i"
        ],
        [
            "e",
            "Te faa",
            "een¬",
            "¬",
            "ſßu .",
            "SA",
            "a",
            "t",
            "28.",
            "ES",
            "e",
            "r",
            "e l",
            "au",
            "d",
            "I .",
            "N",
            "ll",
            "MR",
            "9",
            "Nl",
            "r¬",
            "aar¬",
            "a",
            "¬",
            "eae",
            "S",
            "1",
            "T1",
            "EN",
            "aëi",
            "s ¬",
            "lLl",
            "E A",
            "A",
            "G",
            "tſ",
            "l",
            "2",
            "AA Aet",
            "-",
            "S",
            "Qe",
            "e",
            "3",
            "-8.",
            "ul!",
            "E",
            "l ap",
            "R",
            "V 2",
            "JR u",
            "M",
            "a"
        ]
    ]
}