{
    "imprimatur": null,
    "corrector": false,
    "entête": {
        "form": "prose",
        "genre": "non renseigné",
        "subgenre": [
            null,
            null
        ],
        "subject": null,
        "handwritten_note": false,
        "table_of_content": false,
        "illustration": false,
        "change": {
            "@status": "not_corrected"
        },
        "titre": "Lettre des députés du Parlement à nos seigneurs\n                    de la Cour, avec les circonstances de la mort de Manzini (sic), neveu du\n                    Mazarin, et ce qui s'est passé en la réception du sieur de Rohan, en la qualité\n                    de duc et pair de France.",
        "dates": {
            "@type": "file_creation",
            "@when": "2021-11-02",
            "#text": "2 novembre 2021"
        },
        "author": {
            "persName": {
                "forename": null,
                "surname": null
            }
        },
        "pubDate": {
            "@source": "Moreau",
            "@when": "1652",
            "#text": "1652"
        },
        "pubPlace": {
            "@ref": "geonames:2988507",
            "@source": "Moreau",
            "#text": "Paris"
        },
        "publisher": {
            "@ref": "isni:0000000",
            "persName": {
                "forename": null,
                "surname": null
            }
        },
        "nbPages": "s.i"
    },
    "texte": [
        [
            "r r¬ ¬ E q",
            "1 H",
            "1 4",
            "L L L I. IL",
            "r r7",
            "DV PARLEMENT.",
            "A NOSSEIGNE VRS",
            "DE LA COVR.",
            "EC LES IRCONSTANCES DE LA MoRT",
            "DE MAN2NI, NEVE D AAR.",
            "ET",
            "CE QVI SEST PASSE’EN LA RECEPTON",
            "du Sieur de Rohan, en la qualiteé",
            "de Duc &amp; Pair de France.",
            "A PAR1S,",
            "hez IAeon Cnn v Atra pres Sint Iea¬",
            "de Latran.",
            "M. DC. LII",
            "3l"
        ],
        [
            "¬",
            "1",
            "¬",
            "E",
            "1e",
            "¬",
            "¬",
            "m",
            "¬",
            "e hu",
            "r¬",
            "1 ¬",
            "¬",
            "2",
            "-",
            "oaSoie"
        ],
        [
            "tgsus",
            "o &amp;odas",
            "T r e¬",
            "LETTRE",
            "Des Deputez du Parlement, a No",
            "ſeineurs de la Cour. Auec les",
            "Circonſtances de la Mort de",
            "Manini neueu du Cardinal, &amp;",
            "ce qui eſt paſſ́ en la recepuon",
            "du Sieur de Rohan, en la qua¬",
            "Iité de Due, &amp; Pair de Erance.",
            "ESSEvS,.",
            "Auſſi- toſt que nous receuſmes hiervé̂tre rreſ,,",
            "apres ’auoir conſideré entre nous pour preadr",
            "nos reſolutions , nous le portaſnsendiMoenor",
            "Garde des Seaux pour luy commoier, &amp; le",
            "prier de nous preſenterà la Maieſte pour luy fau¬.",
            "re connoiſtre les lentimensde ſon Alteſſe Royale,",
            "&amp; ceux de toute la Compagnie. Nous eſperons",
            "auoir Audiene demain, &amp; ferons enſorte deng",
            "A 3"
        ],
        [
            "4",
            "le oubller de ce qui eſt de noſtre deuoir pou",
            "obrentr du Roy qu’il eſloigne au pluſtoſt le Car¬",
            "dinal Mzrin, ſuiuant ſes promeſſes &amp; ſa Decla¬",
            "ration, puiſque c’eſt leſeul remede qui peut cal¬",
            "auaer la bonne Ville de Paris, &amp; mertre tout le",
            "Royauine en Pailx. Si nous ſommes aſſés heureu",
            "pour-oparer quelques hoſe parmy tant d’erdur¬",
            "cſſemens, nous en atriburons roure la gloireà̀",
            "ieu, &amp; taſcuerons de vous en porter les nou¬.",
            "uellés nous meſmes, ſi-on nous donne la liberé",
            "enous rendre aupreés de vous, &amp; de vous aller",
            "ſurer des oeïiſſances de",
            "ESSIEVRS.",
            "Vos tres-humbles, &amp;e.",
            "ilet 134 11",
            "p",
            "7",
            "Sae ae 4¬",
            ".l",
            ".. ...-",
            "3",
            "Ceé"
        ],
        [
            "Cette Letrre qui n’eſt rompdie que d’eſperane,",
            "a eſté luiuie d’vne nouuelle qui peut nous perſua¬",
            "der que Dieu commence d’exaucer nos prieres,9",
            "&amp; de vouloir adoucir nos maux, puis qu’il a ap¬",
            "pellé à ſoy le Manaini nepueu du Mazarin, &amp;",
            "Fauori du Roy.",
            "Fncore qu’il ſoit deffendu à̀ rout bon Chreſ¬",
            "tien de ſe reſiouir de la mort de qui que ce ſoit,",
            "neantmoins comme Dieu ne fat rien que pour",
            "ſa gloire, &amp; pour noſtre plus grand bien, ſi nous",
            "demeurons ndfferens dedans la perte de nos e n¬",
            "nemis, nous pouuons rendre grace au rour puiſ¬",
            "ſant lors qu’il nous en deliure, &amp; que nous ne",
            "contribuons rien à cela que noſtre conformité aà̀",
            "ſes ſainétes &amp; adorables volonté́s.",
            "Puis que ce jeune Fauory aageé́ de dixhuiét",
            "ans eſtoit la cauſe que ſon Oncle ne pouuot ſe",
            "deſtacher de la Cour, &amp; que le Roy ne vouloit",
            "pas ſortir de Sainct Denis pendaut la maladie,",
            "nous deuons eſperer maintenant que ce proſ¬",
            "cript eſtranger ira garder ſon ban ,a que ſa M¬",
            "ieſté́ rerirera ſes Trouppes des enuirons de ſa",
            "Capitale, &amp; d vne place qui ne demande &amp; qui",
            "ne reſpire que l’honaeur de ſapreſence. S’ileſt vray",
            "ce que les gens de bien publient auec des larmes",
            "de fang, &amp; des louſpirs qui laur percant le cœur,",
            "que ce petit Italien aage de. cinq ana plus. que"
        ],
        [
            "ſ Majeſté, f ſoit tous ſes efforts pour I’inſtruire1",
            "&amp; la porter d lans toutes ſortes de vices, &amp; de",
            "desbauchess nus auons grande raiſon de croire",
            "que le Ciel n’a pû permettre que ſon DIE.",
            "DONNE, &amp; ſon LOV1S 14., degenerât",
            "de la vertu de ſes anceſtres, &amp; que du fruit de",
            "nos vœux &amp; de nos prieres, vn infame &amp; vn",
            "impie en fit le ſujet de nos malheurs &amp; de nds",
            "maledictions.",
            "C’eſt aſſez que l’Oncle ait tant abuſeé de la can¬",
            "deur &amp; de la probité d’vne Reyne qui paſſoit pour",
            "Saincte quand vn luſte l’a gouuernoit, &amp; qui eſt",
            "deuenue la haine &amp; l’auerſion des peuples, quand",
            "vn Tyran &amp; vn melchant à mieux aymeé s’enri¬",
            "chir, que de conſeruer ſon honneur &amp; ſa repu¬",
            "tation, puis que le fils eſt deſchargé du corrup¬",
            "teur de les mœurs, le meſme Liberateur ttaual¬",
            "lera bien-toſt tres-aſſeurment à deliurer la mere",
            "de la honte &amp; de l’opprobre qui ſemble ternir le",
            "-luſtre de ſa gloire, &amp; l’eſclat de ſa probité De¬",
            "mandons cette grace au Protecteur des Roys &amp;",
            "des Royaumes, &amp; pour l’obtenir plus facilement",
            "&amp; plus promptement, ceſſons de l’offencer, fai¬",
            "ſons penitence, excerçons les bonnes œuures, &amp;",
            "donnons aux pauures vne partie de ce que des",
            "Soldas ennemis nous arrachent &amp; nous empor¬",
            "tent tous les iours ſans iuſtice pour eux, &amp; ſans",
            "A"
        ],
        [
            "merite pour nous, &amp; viuans de la ſorte, nouis",
            "verrons Paris en repos, le Royaume en paix, le",
            "commerce reſtably, le Mzarin chaſſé, le Roy",
            "aupres de nous, le Sang Royal vny, les peuples",
            "r’alliez, &amp; la iuſtice exercé́e ſans trouble &amp; ſans",
            "violence.",
            "Si la corruption de l’vn, eſt la gencration de",
            "l’autre, en apprenant la mort du Marzini, nous",
            "auons veu eſleuer à la dignité́ de Duc &amp; Pair de",
            "France le ſieur Chabot par Arreſt du Parlement",
            "du 5. Iuiller i52. nonobſtant les oppoſitions de",
            "quatre Seigneurs de ſeruice &amp; de reputation qui",
            "ſont auſſi conſiderables, &amp; auſſi bien pourueus",
            "de breuets, &amp; de ce qui eſt neceſſire pour par¬",
            "uenir à̀ cette qualiteé proſtitue, &amp; trop commu¬",
            "ne maintenant. Neantmoins puiſque le ſieur",
            "Chabot a eſpouſeé ce riltre &amp; cét honneur en ſe",
            "mariant à la fille du Duc de Rohan, qu’il ioüyſ¬",
            "ſe de ſa bonne fortune, &amp; qu’l remercie Son",
            "Alteſſe Royale, Monſieur le Prinee, &amp; le Parle.",
            "ment de l’auoir ſi fauorablement preferé à̀ tant",
            "d’autres qui teſmoignent par leurs emplois, &amp;",
            "leurs actions qu’ils n’en ſont pas moins dgnes,",
            "&amp; qu’ils en augmenteront le nombre quelque",
            "iour auſſi heureuſement.",
            "FIN."
        ],
        [
            "¬",
            "A",
            "lea on E",
            "1",
            "uono oole"
        ]
    ]
}